{"resourceType":"ValueSet","id":"b8147000-6e57-11ec-a991-e358c9d3813d","text":{"status":"generated","div":"<div xmlns=\"http://www.w3.org/1999/xhtml\"><p>This value set includes codes based on the following rules:</p><ul><li>Include these codes as defined in <a href=\"http://terminology.hl7.org/3.1.0/CodeSystem-icd10CM.html\"><code>http://hl7.org/fhir/sid/icd-10-cm</code></a> version <code>2022</code><table class=\"none\"><tr><td style=\"white-space:nowrap\"><b>Code</b></td><td><b>Display</b></td></tr><tr><td>J70.3</td><td>Chronic drug-induced interstitial lung disorders</td></tr><tr><td>J66.1</td><td>Flax-dressers' disease</td></tr><tr><td>J62.0</td><td>Pneumoconiosis due to talc dust</td></tr><tr><td>J47.9</td><td>Bronchiectasis, uncomplicated</td></tr><tr><td>J70.1</td><td>Chronic and other pulmonary manifestations due to radiation</td></tr><tr><td>J62</td><td>Pneumoconiosis due to dust containing silica</td></tr><tr><td>J63.1</td><td>Bauxite fibrosis (of lung)</td></tr><tr><td>J45.909</td><td>Unspecified asthma, uncomplicated</td></tr><tr><td>J67.8</td><td>Hypersensitivity pneumonitis due to other organic dusts</td></tr><tr><td>J43.0</td><td>Unilateral pulmonary emphysema [MacLeod's syndrome]</td></tr><tr><td>J47.1</td><td>Bronchiectasis with (acute) exacerbation</td></tr><tr><td>I27.81</td><td>Cor pulmonale (chronic)</td></tr><tr><td>J43.9</td><td>Emphysema, unspecified</td></tr><tr><td>J45.901</td><td>Unspecified asthma with (acute) exacerbation</td></tr><tr><td>J63</td><td>Pneumoconiosis due to other inorganic dusts</td></tr><tr><td>J67.2</td><td>Bird fancier's lung</td></tr><tr><td>J67.0</td><td>Farmer's lung</td></tr><tr><td>I27.82</td><td>Chronic pulmonary embolism</td></tr><tr><td>J63.6</td><td>Pneumoconiosis due to other specified inorganic dusts</td></tr><tr><td>J65</td><td>Pneumoconiosis associated with tuberculosis</td></tr><tr><td>J45.52</td><td>Severe persistent asthma with status asthmaticus</td></tr><tr><td>J43.8</td><td>Other emphysema</td></tr><tr><td>J45.42</td><td>Moderate persistent asthma with status asthmaticus</td></tr><tr><td>J67</td><td>Hypersensitivity pneumonitis due to organic dust</td></tr><tr><td>J41.1</td><td>Mucopurulent chronic bronchitis</td></tr><tr><td>J44.0</td><td>Chronic obstructive pulmonary disease with (acute) lower respiratory infection</td></tr><tr><td>J43.1</td><td>Panlobular emphysema</td></tr><tr><td>I27.83</td><td>Eisenmenger's syndrome</td></tr><tr><td>I27.9</td><td>Pulmonary heart disease, unspecified</td></tr><tr><td>J45.998</td><td>Other asthma</td></tr><tr><td>J67.7</td><td>Air conditioner and humidifier lung</td></tr><tr><td>J67.9</td><td>Hypersensitivity pneumonitis due to unspecified organic dust</td></tr><tr><td>J63.3</td><td>Graphite fibrosis (of lung)</td></tr><tr><td>J44</td><td>Other chronic obstructive pulmonary disease</td></tr><tr><td>J66.8</td><td>Airway disease due to other specific organic dusts</td></tr><tr><td>J67.1</td><td>Bagassosis</td></tr><tr><td>J63.5</td><td>Stannosis</td></tr><tr><td>J45.4</td><td>Moderate persistent asthma</td></tr><tr><td>J68.4</td><td>Chronic respiratory conditions due to chemicals, gases, fumes and vapors</td></tr><tr><td>J45.90</td><td>Unspecified asthma</td></tr><tr><td>J42</td><td>Unspecified chronic bronchitis</td></tr><tr><td>J45.991</td><td>Cough variant asthma</td></tr><tr><td>J44.1</td><td>Chronic obstructive pulmonary disease with (acute) exacerbation</td></tr><tr><td>J45.50</td><td>Severe persistent asthma, uncomplicated</td></tr><tr><td>J66.0</td><td>Byssinosis</td></tr><tr><td>J43.2</td><td>Centrilobular emphysema</td></tr><tr><td>J45.21</td><td>Mild intermittent asthma with (acute) exacerbation</td></tr><tr><td>J47</td><td>Bronchiectasis</td></tr><tr><td>J63.4</td><td>Siderosis</td></tr><tr><td>J45.30</td><td>Mild persistent asthma, uncomplicated</td></tr><tr><td>J45.99</td><td>Other asthma</td></tr><tr><td>I27.8</td><td>Other specified pulmonary heart diseases</td></tr><tr><td>J45.9</td><td>Other and unspecified asthma</td></tr><tr><td>J45.22</td><td>Mild intermittent asthma with status asthmaticus</td></tr><tr><td>J45.3</td><td>Mild persistent asthma</td></tr><tr><td>J45.31</td><td>Mild persistent asthma with (acute) exacerbation</td></tr><tr><td>J47.0</td><td>Bronchiectasis with acute lower respiratory infection</td></tr><tr><td>J67.4</td><td>Maltworker's lung</td></tr><tr><td>J44.9</td><td>Chronic obstructive pulmonary disease, unspecified</td></tr><tr><td>J63.2</td><td>Berylliosis</td></tr><tr><td>J45.32</td><td>Mild persistent asthma with status asthmaticus</td></tr><tr><td>J45.990</td><td>Exercise induced bronchospasm</td></tr><tr><td>J45.902</td><td>Unspecified asthma with status asthmaticus</td></tr><tr><td>J40</td><td>Bronchitis, not specified as acute or chronic</td></tr><tr><td>J41.8</td><td>Mixed simple and mucopurulent chronic bronchitis</td></tr><tr><td>J45.5</td><td>Severe persistent asthma</td></tr><tr><td>J61</td><td>Pneumoconiosis due to asbestos and other mineral fibers</td></tr><tr><td>J45.41</td><td>Moderate persistent asthma with (acute) exacerbation</td></tr><tr><td>J66.2</td><td>Cannabinosis</td></tr><tr><td>J45</td><td>Asthma</td></tr><tr><td>J60</td><td>Coalworker's pneumoconiosis</td></tr><tr><td>J63.0</td><td>Aluminosis (of lung)</td></tr><tr><td>J41</td><td>Simple and mucopurulent chronic bronchitis</td></tr><tr><td>J67.3</td><td>Suberosis</td></tr><tr><td>J66</td><td>Airway disease due to specific organic dust</td></tr><tr><td>J45.51</td><td>Severe persistent asthma with (acute) exacerbation</td></tr><tr><td>I27.89</td><td>Other specified pulmonary heart diseases</td></tr><tr><td>J43</td><td>Emphysema</td></tr><tr><td>J67.5</td><td>Mushroom-worker's lung</td></tr><tr><td>J41.0</td><td>Simple chronic bronchitis</td></tr><tr><td>J45.20</td><td>Mild intermittent asthma, uncomplicated</td></tr><tr><td>J62.8</td><td>Pneumoconiosis due to other dust containing silica</td></tr><tr><td>J45.40</td><td>Moderate persistent asthma, uncomplicated</td></tr><tr><td>J45.2</td><td>Mild intermittent asthma</td></tr><tr><td>J64</td><td>Unspecified pneumoconiosis</td></tr><tr><td>J67.6</td><td>Maple-bark-stripper's lung</td></tr></table></li><li>Include these codes as defined in <a href=\"http://www.snomed.org/\"><code>http://snomed.info/sct</code></a> version <code>2021</code><table class=\"none\"><tr><td style=\"white-space:nowrap\"><b>Code</b></td><td><b>Display</b></td></tr><tr><td><a href=\"http://snomed.info/id/707534000\">707534000</a></td><td>Chronic lung disease due to surfactant disorder (disorder)</td></tr><tr><td><a href=\"http://snomed.info/id/266404004\">266404004</a></td><td>Chronic chemical respiratory disease (disorder)</td></tr><tr><td><a href=\"http://snomed.info/id/135836000\">135836000</a></td><td>End stage chronic obstructive airways disease (disorder)</td></tr><tr><td><a href=\"http://snomed.info/id/77690003\">77690003</a></td><td>Interstitial emphysema of lung (disorder)</td></tr><tr><td><a href=\"http://snomed.info/id/434301000124102\">434301000124102</a></td><td>Chronic interstitial lung disease (disorder)</td></tr><tr><td><a href=\"http://snomed.info/id/47938003\">47938003</a></td><td>Chronic obliterative bronchiolitis (disorder)</td></tr><tr><td><a href=\"http://snomed.info/id/233762004\">233762004</a></td><td>Chronic silicosis (disorder)</td></tr><tr><td><a href=\"http://snomed.info/id/240742009\">240742009</a></td><td>Chronic pulmonary African histoplasmosis (disorder)</td></tr><tr><td><a href=\"http://snomed.info/id/313299006\">313299006</a></td><td>Severe chronic obstructive pulmonary disease (disorder)</td></tr><tr><td><a href=\"http://snomed.info/id/699014000\">699014000</a></td><td>Recurrent pneumonia (disorder)</td></tr><tr><td><a href=\"http://snomed.info/id/723829000\">723829000</a></td><td>Pulmonary fibrosis, hepatic hyperplasia, bone marrow hypoplasia syndrome (disorder)</td></tr><tr><td><a href=\"http://snomed.info/id/28791000119105\">28791000119105</a></td><td>Chronic coccidioidomycotic pneumonia (disorder)</td></tr><tr><td><a href=\"http://snomed.info/id/23958009\">23958009</a></td><td>Vanishing lung (disorder)</td></tr><tr><td><a href=\"http://snomed.info/id/233675009\">233675009</a></td><td>Toxic emphysema (disorder)</td></tr><tr><td><a href=\"http://snomed.info/id/771306007\">771306007</a></td><td>Hereditary fibrosing poikiloderma, tendon contractures, myopathy, pulmonary fibrosis syndrome (disorder)</td></tr><tr><td><a href=\"http://snomed.info/id/313296004\">313296004</a></td><td>Mild chronic obstructive pulmonary disease (disorder)</td></tr><tr><td><a href=\"http://snomed.info/id/1010670004\">1010670004</a></td><td>Chronic endogenous lipoid pneumonia (disorder)</td></tr><tr><td><a href=\"http://snomed.info/id/36599006\">36599006</a></td><td>Chronic fibrosis of lung (disorder)</td></tr><tr><td><a href=\"http://snomed.info/id/86680006\">86680006</a></td><td>Ruptured emphysematous bleb of lung (disorder)</td></tr><tr><td><a href=\"http://snomed.info/id/33325001\">33325001</a></td><td>Compensatory emphysema (disorder)</td></tr><tr><td><a href=\"http://snomed.info/id/106001000119101\">106001000119101</a></td><td>Chronic obstructive lung disease co-occurrent with acute bronchitis (disorder)</td></tr><tr><td><a href=\"http://snomed.info/id/430969000\">430969000</a></td><td>Recurrent aspiration pneumonia (disorder)</td></tr><tr><td><a href=\"http://snomed.info/id/18354001\">18354001</a></td><td>Chronic induration of lung (disorder)</td></tr><tr><td><a href=\"http://snomed.info/id/123713005\">123713005</a></td><td>Chronic atelectasis (disorder)</td></tr><tr><td><a href=\"http://snomed.info/id/240747003\">240747003</a></td><td>Chronic pulmonary blastomycosis (disorder)</td></tr><tr><td><a href=\"http://snomed.info/id/102361000119104\">102361000119104</a></td><td>Chronic pneumonia (disorder)</td></tr><tr><td><a href=\"http://snomed.info/id/708030004\">708030004</a></td><td>Pulmonary emphysema co-occurrent with fibrosis of lung (disorder)</td></tr><tr><td><a href=\"http://snomed.info/id/840350008\">840350008</a></td><td>Chronic obliterative bronchiolitis caused by chemical fumes (disorder)</td></tr><tr><td><a href=\"http://snomed.info/id/195959009\">195959009</a></td><td>Zonal bullous emphysema (disorder)</td></tr><tr><td><a href=\"http://snomed.info/id/460561000124109\">460561000124109</a></td><td>Progressive fibrosing interstitial lung disease (disorder)</td></tr><tr><td><a href=\"http://snomed.info/id/1010334009\">1010334009</a></td><td>Emphysema of right lung (disorder)</td></tr><tr><td><a href=\"http://snomed.info/id/783182004\">783182004</a></td><td>Chronic respiratory distress with surfactant metabolism deficiency (disorder)</td></tr><tr><td><a href=\"http://snomed.info/id/57686001\">57686001</a></td><td>Emphysematous bleb of lung (disorder)</td></tr><tr><td><a href=\"http://snomed.info/id/413839001\">413839001</a></td><td>Chronic lung disease (disorder)</td></tr><tr><td><a href=\"http://snomed.info/id/26427008\">26427008</a></td><td>Chronic pulmonary histoplasmosis (disorder)</td></tr><tr><td><a href=\"http://snomed.info/id/1010333003\">1010333003</a></td><td>Emphysema of left lung (disorder)</td></tr><tr><td><a href=\"http://snomed.info/id/313297008\">313297008</a></td><td>Moderate chronic obstructive pulmonary disease (disorder)</td></tr><tr><td><a href=\"http://snomed.info/id/707553005\">707553005</a></td><td>Chronic exogenous lipoid pneumonia (disorder)</td></tr><tr><td><a href=\"http://snomed.info/id/195957006\">195957006</a></td><td>Chronic bullous emphysema (disorder)</td></tr><tr><td><a href=\"http://snomed.info/id/4981000\">4981000</a></td><td>Panacinar emphysema (disorder)</td></tr><tr><td><a href=\"http://snomed.info/id/836477007\">836477007</a></td><td>Chronic emphysema caused by vapor (disorder)</td></tr><tr><td><a href=\"http://snomed.info/id/10692761000119107\">10692761000119107</a></td><td>Asthma-chronic obstructive pulmonary disease overlap syndrome (disorder)</td></tr><tr><td><a href=\"http://snomed.info/id/16846004\">16846004</a></td><td>Obstructive emphysema (disorder)</td></tr><tr><td><a href=\"http://snomed.info/id/426437004\">426437004</a></td><td>Familial idiopathic pulmonary fibrosis (disorder)</td></tr><tr><td><a href=\"http://snomed.info/id/18121009\">18121009</a></td><td>Chronic berylliosis (disorder)</td></tr><tr><td><a href=\"http://snomed.info/id/789574002\">789574002</a></td><td>Acute exacerbation of idiopathic pulmonary fibrosis (disorder)</td></tr><tr><td><a href=\"http://snomed.info/id/46847001\">46847001</a></td><td>Chronic pulmonary edema (disorder)</td></tr><tr><td><a href=\"http://snomed.info/id/266355005\">266355005</a></td><td>Bullous emphysema with collapse (disorder)</td></tr><tr><td><a href=\"http://snomed.info/id/37180002\">37180002</a></td><td>Chronic nonspecific lung disease (disorder)</td></tr><tr><td><a href=\"http://snomed.info/id/63841001\">63841001</a></td><td>Chronic pulmonary congestion (disorder)</td></tr><tr><td><a href=\"http://snomed.info/id/87433001\">87433001</a></td><td>Pulmonary emphysema (disorder)</td></tr><tr><td><a href=\"http://snomed.info/id/733171006\">733171006</a></td><td>Chronic pulmonary aspergillosis (disorder)</td></tr><tr><td><a href=\"http://snomed.info/id/60805002\">60805002</a></td><td>Hemolytic anemia with emphysema AND cutis laxa (disorder)</td></tr><tr><td><a href=\"http://snomed.info/id/31898008\">31898008</a></td><td>Paraseptal emphysema (disorder)</td></tr><tr><td><a href=\"http://snomed.info/id/233713004\">233713004</a></td><td>Seasonal cryptogenic organizing pneumonia with biochemical cholestasis (disorder)</td></tr><tr><td><a href=\"http://snomed.info/id/432958009\">432958009</a></td><td>Chronic rejection of lung transplant (disorder)</td></tr><tr><td><a href=\"http://snomed.info/id/266356006\">266356006</a></td><td>Atrophic (senile) emphysema (disorder)</td></tr><tr><td><a href=\"http://snomed.info/id/713525001\">713525001</a></td><td>Recurrent bacterial pneumonia (disorder)</td></tr><tr><td><a href=\"http://snomed.info/id/700250006\">700250006</a></td><td>Idiopathic pulmonary fibrosis (disorder)</td></tr><tr><td><a href=\"http://snomed.info/id/704345008\">704345008</a></td><td>Chronic interstitial pneumonia (disorder)</td></tr><tr><td><a href=\"http://snomed.info/id/846637007\">846637007</a></td><td>Chronic pulmonary fibrosis caused by chemical vapors (disorder)</td></tr><tr><td><a href=\"http://snomed.info/id/195958001\">195958001</a></td><td>Segmental bullous emphysema (disorder)</td></tr><tr><td><a href=\"http://snomed.info/id/233674008\">233674008</a></td><td>Pulmonary emphysema in alpha-1 primary immunodeficiency deficiency (disorder)</td></tr><tr><td><a href=\"http://snomed.info/id/737180005\">737180005</a></td><td>Chronic bronchiolitis (disorder)</td></tr><tr><td><a href=\"http://snomed.info/id/196001008\">196001008</a></td><td>Chronic obstructive pulmonary disease with acute lower respiratory infection (disorder)</td></tr><tr><td><a href=\"http://snomed.info/id/285381006\">285381006</a></td><td>Acute infective exacerbation of chronic obstructive airways disease (disorder)</td></tr><tr><td><a href=\"http://snomed.info/id/430476004\">430476004</a></td><td>Diffuse panbronchiolitis (disorder)</td></tr><tr><td><a href=\"http://snomed.info/id/1751000119100\">1751000119100</a></td><td>Acute exacerbation of chronic obstructive airways disease with asthma (disorder)</td></tr><tr><td><a href=\"http://snomed.info/id/13645005\">13645005</a></td><td>Chronic obstructive lung disease (disorder)</td></tr><tr><td><a href=\"http://snomed.info/id/195951007\">195951007</a></td><td>Acute exacerbation of chronic obstructive airways disease (disorder)</td></tr><tr><td><a href=\"http://snomed.info/id/233677001\">233677001</a></td><td>Scar emphysema (disorder)</td></tr><tr><td><a href=\"http://snomed.info/id/2912004\">2912004</a></td><td>Cystic-bullous disease of the lung (disorder)</td></tr><tr><td><a href=\"http://snomed.info/id/16003001\">16003001</a></td><td>Giant bullous emphysema (disorder)</td></tr><tr><td><a href=\"http://snomed.info/id/417688002\">417688002</a></td><td>Chronic progressive coccidioidal pneumonia (disorder)</td></tr><tr><td><a href=\"http://snomed.info/id/47895001\">47895001</a></td><td>Congenital emphysema (disorder)</td></tr><tr><td><a href=\"http://snomed.info/id/314954002\">314954002</a></td><td>Local recurrence of malignant tumor of lung (disorder)</td></tr><tr><td><a href=\"http://snomed.info/id/196026004\">196026004</a></td><td>Chronic emphysema caused by chemical fumes (disorder)</td></tr><tr><td><a href=\"http://snomed.info/id/233615002\">233615002</a></td><td>Chronic pulmonary coccidioidomycosis (disorder)</td></tr><tr><td><a href=\"http://snomed.info/id/713526000\">713526000</a></td><td>Recurrent bacterial pneumonia co-occurrent with human immunodeficiency virus infection (disorder)</td></tr><tr><td><a href=\"http://snomed.info/id/196028003\">196028003</a></td><td>Chronic pulmonary fibrosis caused by chemical fumes (disorder)</td></tr><tr><td><a href=\"http://snomed.info/id/840351007\">840351007</a></td><td>Chronic obliterative bronchiolitis caused by vapor (disorder)</td></tr><tr><td><a href=\"http://snomed.info/id/196049002\">196049002</a></td><td>Chronic pulmonary radiation disease (disorder)</td></tr><tr><td><a href=\"http://snomed.info/id/724500003\">724500003</a></td><td>Idiopathic chronic eosinophilic pneumonia (disorder)</td></tr><tr><td><a href=\"http://snomed.info/id/70756004\">70756004</a></td><td>Bronchial atresia with segmental pulmonary emphysema (disorder)</td></tr><tr><td><a href=\"http://snomed.info/id/68328006\">68328006</a></td><td>Centriacinar emphysema (disorder)</td></tr><tr><td><a href=\"http://snomed.info/id/66987001\">66987001</a></td><td>Congenital lobar emphysema (disorder)</td></tr></table></li></ul></div>"},"url":"http://projectronin.com/fhir/us/ronin/ValueSet/b8147000-6e57-11ec-a991-e358c9d3813d","version":"0.9.5","name":"ChronicPulmonaryDisease","title":"Chronic Pulmonary Disease","status":"active","experimental":false,"date":"2022-03-14T18:28:42+00:00","publisher":"Project Ronin Inc.","contact":[{"name":"Project Ronin Inc.","telecom":[{"system":"url","value":"https://www.projectronin.com"},{"system":"email","value":"contact@projectronin.com"}]}],"description":"SNOMED and ICD10 codes for the condition of Chronic Pulmonary Disease","jurisdiction":[{"coding":[{"system":"urn:iso:std:iso:3166","code":"US","display":"United States of America"}]}],"immutable":false,"compose":{"include":[{"system":"http://hl7.org/fhir/sid/icd-10-cm","version":"2022","concept":[{"code":"J70.3","display":"Chronic drug-induced interstitial lung disorders"},{"code":"J66.1","display":"Flax-dressers' disease"},{"code":"J62.0","display":"Pneumoconiosis due to talc dust"},{"code":"J47.9","display":"Bronchiectasis, uncomplicated"},{"code":"J70.1","display":"Chronic and other pulmonary manifestations due to radiation"},{"code":"J62","display":"Pneumoconiosis due to dust containing silica"},{"code":"J63.1","display":"Bauxite fibrosis (of lung)"},{"code":"J45.909","display":"Unspecified asthma, uncomplicated"},{"code":"J67.8","display":"Hypersensitivity pneumonitis due to other organic dusts"},{"code":"J43.0","display":"Unilateral pulmonary emphysema [MacLeod's syndrome]"},{"code":"J47.1","display":"Bronchiectasis with (acute) exacerbation"},{"code":"I27.81","display":"Cor pulmonale (chronic)"},{"code":"J43.9","display":"Emphysema, unspecified"},{"code":"J45.901","display":"Unspecified asthma with (acute) exacerbation"},{"code":"J63","display":"Pneumoconiosis due to other inorganic dusts"},{"code":"J67.2","display":"Bird fancier's lung"},{"code":"J67.0","display":"Farmer's lung"},{"code":"I27.82","display":"Chronic pulmonary embolism"},{"code":"J63.6","display":"Pneumoconiosis due to other specified inorganic dusts"},{"code":"J65","display":"Pneumoconiosis associated with tuberculosis"},{"code":"J45.52","display":"Severe persistent asthma with status asthmaticus"},{"code":"J43.8","display":"Other emphysema"},{"code":"J45.42","display":"Moderate persistent asthma with status asthmaticus"},{"code":"J67","display":"Hypersensitivity pneumonitis due to organic dust"},{"code":"J41.1","display":"Mucopurulent chronic bronchitis"},{"code":"J44.0","display":"Chronic obstructive pulmonary disease with (acute) lower respiratory infection"},{"code":"J43.1","display":"Panlobular emphysema"},{"code":"I27.83","display":"Eisenmenger's syndrome"},{"code":"I27.9","display":"Pulmonary heart disease, unspecified"},{"code":"J45.998","display":"Other asthma"},{"code":"J67.7","display":"Air conditioner and humidifier lung"},{"code":"J67.9","display":"Hypersensitivity pneumonitis due to unspecified organic dust"},{"code":"J63.3","display":"Graphite fibrosis (of lung)"},{"code":"J44","display":"Other chronic obstructive pulmonary disease"},{"code":"J66.8","display":"Airway disease due to other specific organic dusts"},{"code":"J67.1","display":"Bagassosis"},{"code":"J63.5","display":"Stannosis"},{"code":"J45.4","display":"Moderate persistent asthma"},{"code":"J68.4","display":"Chronic respiratory conditions due to chemicals, gases, fumes and vapors"},{"code":"J45.90","display":"Unspecified asthma"},{"code":"J42","display":"Unspecified chronic bronchitis"},{"code":"J45.991","display":"Cough variant asthma"},{"code":"J44.1","display":"Chronic obstructive pulmonary disease with (acute) exacerbation"},{"code":"J45.50","display":"Severe persistent asthma, uncomplicated"},{"code":"J66.0","display":"Byssinosis"},{"code":"J43.2","display":"Centrilobular emphysema"},{"code":"J45.21","display":"Mild intermittent asthma with (acute) exacerbation"},{"code":"J47","display":"Bronchiectasis"},{"code":"J63.4","display":"Siderosis"},{"code":"J45.30","display":"Mild persistent asthma, uncomplicated"},{"code":"J45.99","display":"Other asthma"},{"code":"I27.8","display":"Other specified pulmonary heart diseases"},{"code":"J45.9","display":"Other and unspecified asthma"},{"code":"J45.22","display":"Mild intermittent asthma with status asthmaticus"},{"code":"J45.3","display":"Mild persistent asthma"},{"code":"J45.31","display":"Mild persistent asthma with (acute) exacerbation"},{"code":"J47.0","display":"Bronchiectasis with acute lower respiratory infection"},{"code":"J67.4","display":"Maltworker's lung"},{"code":"J44.9","display":"Chronic obstructive pulmonary disease, unspecified"},{"code":"J63.2","display":"Berylliosis"},{"code":"J45.32","display":"Mild persistent asthma with status asthmaticus"},{"code":"J45.990","display":"Exercise induced bronchospasm"},{"code":"J45.902","display":"Unspecified asthma with status asthmaticus"},{"code":"J40","display":"Bronchitis, not specified as acute or chronic"},{"code":"J41.8","display":"Mixed simple and mucopurulent chronic bronchitis"},{"code":"J45.5","display":"Severe persistent asthma"},{"code":"J61","display":"Pneumoconiosis due to asbestos and other mineral fibers"},{"code":"J45.41","display":"Moderate persistent asthma with (acute) exacerbation"},{"code":"J66.2","display":"Cannabinosis"},{"code":"J45","display":"Asthma"},{"code":"J60","display":"Coalworker's pneumoconiosis"},{"code":"J63.0","display":"Aluminosis (of lung)"},{"code":"J41","display":"Simple and mucopurulent chronic bronchitis"},{"code":"J67.3","display":"Suberosis"},{"code":"J66","display":"Airway disease due to specific organic dust"},{"code":"J45.51","display":"Severe persistent asthma with (acute) exacerbation"},{"code":"I27.89","display":"Other specified pulmonary heart diseases"},{"code":"J43","display":"Emphysema"},{"code":"J67.5","display":"Mushroom-worker's lung"},{"code":"J41.0","display":"Simple chronic bronchitis"},{"code":"J45.20","display":"Mild intermittent asthma, uncomplicated"},{"code":"J62.8","display":"Pneumoconiosis due to other dust containing silica"},{"code":"J45.40","display":"Moderate persistent asthma, uncomplicated"},{"code":"J45.2","display":"Mild intermittent asthma"},{"code":"J64","display":"Unspecified pneumoconiosis"},{"code":"J67.6","display":"Maple-bark-stripper's lung"}]},{"system":"http://snomed.info/sct","version":"2021","concept":[{"code":"707534000","display":"Chronic lung disease due to surfactant disorder (disorder)"},{"code":"266404004","display":"Chronic chemical respiratory disease (disorder)"},{"code":"135836000","display":"End stage chronic obstructive airways disease (disorder)"},{"code":"77690003","display":"Interstitial emphysema of lung (disorder)"},{"code":"434301000124102","display":"Chronic interstitial lung disease (disorder)"},{"code":"47938003","display":"Chronic obliterative bronchiolitis (disorder)"},{"code":"233762004","display":"Chronic silicosis (disorder)"},{"code":"240742009","display":"Chronic pulmonary African histoplasmosis (disorder)"},{"code":"313299006","display":"Severe chronic obstructive pulmonary disease (disorder)"},{"code":"699014000","display":"Recurrent pneumonia (disorder)"},{"code":"723829000","display":"Pulmonary fibrosis, hepatic hyperplasia, bone marrow hypoplasia syndrome (disorder)"},{"code":"28791000119105","display":"Chronic coccidioidomycotic pneumonia (disorder)"},{"code":"23958009","display":"Vanishing lung (disorder)"},{"code":"233675009","display":"Toxic emphysema (disorder)"},{"code":"771306007","display":"Hereditary fibrosing poikiloderma, tendon contractures, myopathy, pulmonary fibrosis syndrome (disorder)"},{"code":"313296004","display":"Mild chronic obstructive pulmonary disease (disorder)"},{"code":"1010670004","display":"Chronic endogenous lipoid pneumonia (disorder)"},{"code":"36599006","display":"Chronic fibrosis of lung (disorder)"},{"code":"86680006","display":"Ruptured emphysematous bleb of lung (disorder)"},{"code":"33325001","display":"Compensatory emphysema (disorder)"},{"code":"106001000119101","display":"Chronic obstructive lung disease co-occurrent with acute bronchitis (disorder)"},{"code":"430969000","display":"Recurrent aspiration pneumonia (disorder)"},{"code":"18354001","display":"Chronic induration of lung (disorder)"},{"code":"123713005","display":"Chronic atelectasis (disorder)"},{"code":"240747003","display":"Chronic pulmonary blastomycosis (disorder)"},{"code":"102361000119104","display":"Chronic pneumonia (disorder)"},{"code":"708030004","display":"Pulmonary emphysema co-occurrent with fibrosis of lung (disorder)"},{"code":"840350008","display":"Chronic obliterative bronchiolitis caused by chemical fumes (disorder)"},{"code":"195959009","display":"Zonal bullous emphysema (disorder)"},{"code":"460561000124109","display":"Progressive fibrosing interstitial lung disease (disorder)"},{"code":"1010334009","display":"Emphysema of right lung (disorder)"},{"code":"783182004","display":"Chronic respiratory distress with surfactant metabolism deficiency (disorder)"},{"code":"57686001","display":"Emphysematous bleb of lung (disorder)"},{"code":"413839001","display":"Chronic lung disease (disorder)"},{"code":"26427008","display":"Chronic pulmonary histoplasmosis (disorder)"},{"code":"1010333003","display":"Emphysema of left lung (disorder)"},{"code":"313297008","display":"Moderate chronic obstructive pulmonary disease (disorder)"},{"code":"707553005","display":"Chronic exogenous lipoid pneumonia (disorder)"},{"code":"195957006","display":"Chronic bullous emphysema (disorder)"},{"code":"4981000","display":"Panacinar emphysema (disorder)"},{"code":"836477007","display":"Chronic emphysema caused by vapor (disorder)"},{"code":"10692761000119107","display":"Asthma-chronic obstructive pulmonary disease overlap syndrome (disorder)"},{"code":"16846004","display":"Obstructive emphysema (disorder)"},{"code":"426437004","display":"Familial idiopathic pulmonary fibrosis (disorder)"},{"code":"18121009","display":"Chronic berylliosis (disorder)"},{"code":"789574002","display":"Acute exacerbation of idiopathic pulmonary fibrosis (disorder)"},{"code":"46847001","display":"Chronic pulmonary edema (disorder)"},{"code":"266355005","display":"Bullous emphysema with collapse (disorder)"},{"code":"37180002","display":"Chronic nonspecific lung disease (disorder)"},{"code":"63841001","display":"Chronic pulmonary congestion (disorder)"},{"code":"87433001","display":"Pulmonary emphysema (disorder)"},{"code":"733171006","display":"Chronic pulmonary aspergillosis (disorder)"},{"code":"60805002","display":"Hemolytic anemia with emphysema AND cutis laxa (disorder)"},{"code":"31898008","display":"Paraseptal emphysema (disorder)"},{"code":"233713004","display":"Seasonal cryptogenic organizing pneumonia with biochemical cholestasis (disorder)"},{"code":"432958009","display":"Chronic rejection of lung transplant (disorder)"},{"code":"266356006","display":"Atrophic (senile) emphysema (disorder)"},{"code":"713525001","display":"Recurrent bacterial pneumonia (disorder)"},{"code":"700250006","display":"Idiopathic pulmonary fibrosis (disorder)"},{"code":"704345008","display":"Chronic interstitial pneumonia (disorder)"},{"code":"846637007","display":"Chronic pulmonary fibrosis caused by chemical vapors (disorder)"},{"code":"195958001","display":"Segmental bullous emphysema (disorder)"},{"code":"233674008","display":"Pulmonary emphysema in alpha-1 primary immunodeficiency deficiency (disorder)"},{"code":"737180005","display":"Chronic bronchiolitis (disorder)"},{"code":"196001008","display":"Chronic obstructive pulmonary disease with acute lower respiratory infection (disorder)"},{"code":"285381006","display":"Acute infective exacerbation of chronic obstructive airways disease (disorder)"},{"code":"430476004","display":"Diffuse panbronchiolitis (disorder)"},{"code":"1751000119100","display":"Acute exacerbation of chronic obstructive airways disease with asthma (disorder)"},{"code":"13645005","display":"Chronic obstructive lung disease (disorder)"},{"code":"195951007","display":"Acute exacerbation of chronic obstructive airways disease (disorder)"},{"code":"233677001","display":"Scar emphysema (disorder)"},{"code":"2912004","display":"Cystic-bullous disease of the lung (disorder)"},{"code":"16003001","display":"Giant bullous emphysema (disorder)"},{"code":"417688002","display":"Chronic progressive coccidioidal pneumonia (disorder)"},{"code":"47895001","display":"Congenital emphysema (disorder)"},{"code":"314954002","display":"Local recurrence of malignant tumor of lung (disorder)"},{"code":"196026004","display":"Chronic emphysema caused by chemical fumes (disorder)"},{"code":"233615002","display":"Chronic pulmonary coccidioidomycosis (disorder)"},{"code":"713526000","display":"Recurrent bacterial pneumonia co-occurrent with human immunodeficiency virus infection (disorder)"},{"code":"196028003","display":"Chronic pulmonary fibrosis caused by chemical fumes (disorder)"},{"code":"840351007","display":"Chronic obliterative bronchiolitis caused by vapor (disorder)"},{"code":"196049002","display":"Chronic pulmonary radiation disease (disorder)"},{"code":"724500003","display":"Idiopathic chronic eosinophilic pneumonia (disorder)"},{"code":"70756004","display":"Bronchial atresia with segmental pulmonary emphysema (disorder)"},{"code":"68328006","display":"Centriacinar emphysema (disorder)"},{"code":"66987001","display":"Congenital lobar emphysema (disorder)"}]}]}}